{"rule_id": 114, "name": "2015-2022_textOperation-Blockbuster-Tools-Report", "description": "-", "references": [], "samples": ["pmsconfig.msi", "kr.albn", "mspaint.exe", "VsTskMgr.exe", "zawq.bat", "AUTOEXEO.bat", "McTray.exe", "wsock32.dll", "Report.pdf", "or.kr", "UdaterUI.exe", "boho.or", "FrameworkService.exe", "shstat.exe", "mfeann.exe", "download.boho", "AdobeUpdaterPrefs.dat", "mscorsw.exe", "naPrdMgr.exe", "McShield.exe", "www.boho", "iphapi.dll", "pmslog.msi", "IconCache.dat"], "MD5": [], "SHA1": [], "SHA256": [], "Registry_Entries": ["HKLM\\SYSTEM\\", "HKLM\\Software\\Microsoft\\CurrentVersion\\Run\\Mozilla Update is added "], "URL": ["http://www.operationblockbuster.com/wp-content/uploads/2016/02/Operation-Blockbuster-RAT-and-Staging-Report.pdf", "http://processhacker.sourceforge.net/.", "http://go.microsoft.com/fwlink/?linkid=121488."], "weight": 0.0, "signatures": ["HKLM\\SYSTEM\\", "HKLM\\Software\\Microsoft\\CurrentVersion\\Run\\Mozilla Update is added ", "http://www.operationblockbuster.com/wp-content/uploads/2016/02/Operation-Blockbuster-RAT-and-Staging-Report.pdf", "http://processhacker.sourceforge.net/.", "http://go.microsoft.com/fwlink/?linkid=121488."]}