{"rule_id": 36, "name": "Between Hong Kong and Burma_ Tracking UP007 and SLServer Espionage Campaigns - The Citizen Lab", "description": "-", "references": [], "File_Names": ["nvsvc.exe", "ok.exe", "maindll.dll", "32.zip", "wthk.txt", "fzyy.exe", "\u4e2d\u56fd\u56fd\u5bb6\u5b89\u5168\u59d4\u5458\u4f1a\u673a\u6784\u8bbe\u7f6e\u548c\u4eba\u5458\u540d\u5355\u63d0\u524d\u66dd\u5149.docx", "citizenlab.org", "73\u500b\u7acb\u59d4\u9078\u5340\u9078\u60c5\u7814\u5224.doc", "Keyainst.exe", "dll2.xor", "yeaton.xicp", "minutes.docx", "conhost.exe", "Statement.doc", "chin.jpg", "runas.exe", "\u8072\u660e.doc", "SBieDll.dll", "javaupdata.dll", "Elections.rar", "2016\u7e3d\u7d71\u9078\u8209\u6c11\u60c5\u4e2d\u5fc3\u9810\u6e2c\u503c.doc", "SLServer.pdb", "centers.com", "QiHua.rar", "2016\u7e3d\u7d71\u9078\u8209\u6c11\u60c5\u4e2d\u5fc3\u9810\u6e2c\u503c.rar", "Update.exe", "hihihihihahaha.vicp", "wzget.exe"], "MD5_Hashes": ["e0eb981ad6be0bd16246d5d442028687", "f80edbb0fcfe7cec17592f61a06e4df2", "639c7239f40d95f677a99abb059e8338", "e2ac89b5c820fc598b92a635a7d8bc33", "983333e2c878a62d95747c36748198f0", "19866e7566373028799abd6844ac16d1", "7332245f67b6b8a256ab22a6496b4536", "dc195d814ec16fe91690b7e949e696f6", "82896b68314d108141728a4112618304", "d8ede9e6c3a1a30398b0b98130ee3b38", "d8becbd6f188e3fb2c4d23a2d36d137b", "6a541de84074a2c4ff99eb43252d9030", "cfcd2a90e87156e1a811f9c7b0051002", "397021af7c0284c28db65297a6711235", "820438f3f1efede11425a9cc13ae2dbd", "21455a5c2496e2603f6ba911fbaaed80", "be378f3d66ecd38cda09508015de71f7", "e5e7dcbda781dd0bf5f5da3cccdb094d", "d579d7a42ff140952da57264614c37bc", "09ddd70517cb48a46d9f93644b29c72f", "d07b2738840ce3419df651d3a0a3a246", "ce8ec932be16b69ffa06626b3b423395", "f70b295c6a5121b918682310ce0c2165"], "SHA1_Hashes": [], "SHA256_Hashes": [], "Registry_Entries": ["HKLM\\SOFTWARE\\360Safe\\Liveup\n\ncurl\n\nHKCU\\Software\\360safe\n\nDefaultSkin\n\nHKLM\\SOFTWARE\\kingsoft\\Antivirus\n\nWorkPath\n\nHKLM\\SOFTWARE\\Avira\\Avira Destop\n\nPath\n\nHKLM\\SOFTWARE\\rising\\RAV\n\ninstallpath\n\nHKLM\\SOFTWARE\\JiangMin\n\nInstallPath\n\nHKLM\\SOFTWARE\\Micropoint\\Anti-Attack MP100000\n\nTable\u00a03:\u00a0Registry\u00a0keys\u00a0that\u00a0fzyy.exe\u00a0checks\u00a0for\u00a0before\u00a0writing\u00a0maindll.dll\n\nOnce\u00a0all\u00a0the\u00a0files\u00a0are\u00a0created,\u00a0conhost.exe\u00a0starts,\u00a0loads\u00a0SBieDll.dll,\u00a0then\u00a0ultimately\u00a0loads\u00a0maindll.dll\u00a0and\u00a0the\u00a0final\npayload,\u00a0which\u00a0we\u00a0have\u00a0named\u00a0UP007\u00a0(dll2.xor)\u00a0due\u00a0to\u00a0an\u00a0identifier\u00a0in\u00a0the\u00a0network\u00a0traffic.\u00a0The\u00a0primary\u00a0function\u00a0of\nUP007\u00a0appears\u00a0to\u00a0be\u00a0to\u00a0log\u00a0keystrokes\u00a0to\u00a0the\u00a0%USERPROFILE%\\Local Settings\\Temp\\keylog\\ directory\u00a0and\u00a0send\nthem\u00a0to\u00a0a\u00a0remote\u00a0server.\n\nUP007\u00a0uses\u00a0Windows\u00a0Sockets\u00a0to\u00a0communicate\u00a0with\u00a0its\u00a0command\u00a0and\u00a0control\u00a0server\u00a0(C2).\u00a0While\u00a0doing\u00a0so,\u00a0it\u00a0sends\u00a0a\n\nhardcoded\u00a0HTTP\u00a0header\u00a0disguised\u00a0as\u00a0Microsoft\u00a0Update\u00a0traffic.\u00a0This\u00a0is\u00a0likely\u00a0an\u00a0attempt\u00a0to\u00a0escape\u00a0notice\u00a0by\u00a0casual\n\ninspection\u00a0of\u00a0network\u00a0traffic.\u00a0On\u00a0connection,\u00a0UP007\u00a0downloads\u00a0another\u00a0payload\u00a0directly\u00a0from\u00a0the\u00a0C2\u00a0server.\u00a0This\n\nsecondary\u00a0payload\u00a0we\u00a0have\u00a0named\u00a0\u201cDownLoad\u201d\u00a0given\u00a0the\u00a0way\u00a0it\u00a0identifies\u00a0itself\u00a0in\u00a0the\u00a0traffic\u00a0with\u00a0the\u00a0C2\u00a0server.\u00a0This\n\nsecondary\u00a0payload\u00a0is\u00a0injected\u00a0into\u00a0memory.\u00a0The\u00a0initial\u00a0network\u00a0traffic\u00a0observed\u00a0from\u00a0the\u00a0UP007\u00a0sample\u00a0is\u00a0seen\u00a0in\u00a0Figure\u00a03.\n\nFigure\u00a03:\u00a0Network\u00a0capture\u00a0of\u00a0the\u00a0initial\u00a0communication\u00a0by\u00a0UP007.\n\nOnce\u00a0the\u00a0entire\u00a0payload\u00a0is\u00a0received\u00a0from\u00a0the\u00a0C2\u00a0server,\u00a0UP007\u00a0sends\u00a0basic\u00a0system\u00a0information\u00a0such\u00a0as\u00a0operating\u00a0system\n\nversion,\u00a0IP\u00a0address,\u00a0and\u00a0username\u00a0and\u00a0the\u00a0C2\u00a0responds\u00a0with\u00a0a\u00a0\u201cREADY\u201d\u00a0announcement\u00a0(see\u00a0Figure\u00a04).\n\nFigure\u00a04:\u00a0Network\u00a0capture\u00a0of\u00a0the\u00a0infected\u00a0system\u00a0sending\u00a0system\u00a0information\u00a0to\u00a0the\u00a0C2.\n\nThe\u00a0secondary\u00a0payload\u00a0(DownLoad)\u00a0initiates\u00a0its\u00a0own\u00a0separate\u00a0TCP\u00a0connection\u00a0with\u00a0the\u00a0C2\u00a0server.\u00a0A\u00a0sample\u00a0of\u00a0the\n\nnetwork\u00a0traffic\u00a0of\u00a0this\u00a0secondary\u00a0payload\u00a0is\u00a0seen\u00a0in\u00a0Figure\u00a05.\n\nhttps://citizenlab.org/2016/04/between-hong-kong-and-burma/\n\n4/9\n\n\f2016/4/20\n\nBetween Hong Kong and Burma: Tracking UP007 and SLServer Espionage Campaigns - The Citizen Lab\n\nFigure\u00a05:\u00a0Network\u00a0capture\u00a0of\u00a0DownLoad\u00a0connection\u00a0to\u00a0the\u00a0C2.\n\nUnfortunately,\u00a0even\u00a0though\u00a0the\u00a0connection\u00a0with\u00a0the\u00a0C2\u00a0was\u00a0established,\u00a0we\u00a0did\u00a0not\u00a0observe\u00a0any\u00a0further\u00a0activity\u00a0from\u00a0this\n\npayload.\u00a0However,\u00a0DownLoad\u2019s\u00a0strings\u00a0show\u00a0references\u00a0to\u00a0the\u00a0following:\n\nthis is cmd\n\nthis is Desktop\n\nIt\u00a0is\u00a0possible\u00a0these\u00a0are\u00a0in\u00a0reference\u00a0to\u00a0additional\u00a0components\u00a0or\u00a0capabilities\u00a0of\u00a0the\u00a0malware.\u00a0Further\u00a0analysis\u00a0is\u00a0required\u00a0to\n\ndetermine\u00a0the\u00a0function\u00a0of\u00a0these\u00a0components.\n\nUP007\u00a0Command\u00a0and\u00a0Control\u00a0Infrastructure\n\nThe\u00a0command\u00a0and\u00a0control\u00a0server\u00a0for\u00a0the\u00a0UP007\u00a0sample\u00a0is\u00a0hosted\u00a0on\u00a0Hong\u00a0Kong\u00a0provider\u00a0New\u00a0World\u00a0Telecom\u00a0at\u00a0the\u00a0IP\n\naddress\u00a059.188.12[.]123.\u00a0Passive\u00a0DNS\u00a0data\u00a0from\u00a0PassiveTotal\u00a0indicates\u00a0that\u00a0the\u00a0domain\u00a0name\u00a0yeaton.xicp[.]net\npointed\u00a0to\u00a0this\u00a0IP\u00a0from\u00a0January\u00a08\u00a02016\u00a0to\u00a0March\u00a019\u00a02016.\u00a0In\u00a0their\u00a0recent\u00a0report\u00a0ASERT\u00a0notes\u00a0that\u00a0the\u00a0domain:\n\nyeaton.xicp[.]net\u00a0was\u00a0used\u00a0to\u00a0advertise\u00a0a\u00a0Chinese\u00a0VPN\u00a0service\u00a0in\u00a02012.\u00a0However,\u00a0as\u00a0ASERT\u00a0explains\u00a0given\u00a0the\u00a0long\nperiod\u00a0between\u00a0the\u00a0use\u00a0of\u00a0the\u00a0domain\u00a0for\u00a0advertising\u00a0and\u00a0the\u00a0recent\u00a0threat\u00a0activity\u00a0the\u00a0past\u00a0uses\u00a0of\u00a0the\u00a0domain\u00a0may\u00a0not\n\nbe\u00a0related\u00a0to\u00a0the\u00a0threat\u00a0actors.\n\nUP007\u00a0Samples\u00a0and\u00a0Variations\n\nIn\u00a0November\u00a02013,\u00a0an\u00a0exploit\u00a0document\u00a0(MD5:\u00a0983333e2c878a62d95747c36748198f0)\u00a0was\u00a0uploaded\u00a0to\u00a0various\u00a0malware\n\nsites\u00a0with\u00a0the\u00a0filename\u00a0\u4e2d\u56fd\u56fd\u5bb6\u5b89\u5168\u59d4\u5458\u4f1a\u673a\u6784\u8bbe\u7f6e\u548c\u4eba\u5458\u540d\u5355\u63d0\u524d\u66dd\u5149.docx\u00a0(which\u00a0translates\u00a0to\u00a0\u201cChinese\u00a0National\nSecurity\u00a0Council\u2019s\u00a0Institutional\u00a0Structure\u00a0and\u00a0Member\u00a0list\u201d)\u00a0and\u00a0131106 minutes.docx.\u00a0Instead\u00a0of\u00a0receiving\u00a0the\u00a0Stage\n2\u00a0binary\u00a0in\u00a0the\u00a0C2\u00a0protocol\u00a0as\u00a0in\u00a0the\u00a0recent\u00a0UP007\u00a0sample,\u00a0the\u00a0November\u00a02013\u00a0sample\u00a0directly\u00a0requested\u00a0ok.exe\u00a0via\u00a0an\nHTTP\u00a0GET\u00a0request\u00a0to\u00a0103.19.85[.]89.\u00a0The\u00a0ok.exe\u00a0sample\u00a0communicated\u00a0with\u00a0tenday.mysecondarydns[.]com\u00a0which\nresolved\u00a0to\u00a0103.19.85[.]89.\u00a0It\u00a0was\u00a0signed\u00a0with\u00a0a\u00a0certificate\u00a0with\u00a0serial\u00a0number\u00a004 DE 6E CB 4B A2 A5 54 2B 5E 0C\n71 EE FD 2A AA.\n\nOne\u00a0year\u00a0later,\u00a0in\u00a0November\u00a02014,\u00a0another\u00a0instance\u00a0of\u00a0the\u00a0UP007\u00a0dropper\u00a0(MD5:\u00a0e2ac89b5c820fc598b92a635a7d8bc33)\n\nsigned\u00a0with\u00a0a\u00a0certificate\u00a0using\u00a0the\u00a0serial\u00a0number\u00a03A 72 A8 34 FB EC E5 4F A5 E5 2F 67 BA 63 4D CA\u00a0was\nuploaded\u00a0to\u00a0VirusTotal.\u00a0According\u00a0to\u00a0VirusTotal,\u00a0this\u00a0file\u00a0was\u00a0observed\u00a0being\u00a0hosted\u00a0at\n\nhttp://103.19.85[.]89/chin.jpg.\u00a0The\u00a0final\u00a0payload\u00a0was\u00a0designed\u00a0to\u00a0communicate\u00a0with\u00a0the\u00a0same\u00a0host\u00a0for\ncommand\u00a0and\u00a0control.\n\nIn\u00a0August\u00a02015,\u00a0an\u00a0instance\u00a0of\u00a0the\u00a0UP007\u00a0dropper\u00a0(MD5:\u00a0639c7239f40d95f677a99abb059e8338)\u00a0signed\u00a0with\u00a0the\u00a0same\n\ncertificate\u00a0(Serial:\u00a05D 11 78 4F B8 17 65 02 3F 89 A4 F4 24 3F E1 A9)\u00a0as\u00a0fzyy.exe\u00a0was\u00a0uploaded\u00a0to\u00a0VirusTotal\nspotted\u00a0in\u00a0the\u00a0wild\u00a0as\u00a0http://hkemail.f3322[.]org/32.zip.\u00a0This\u00a0sample\u00a0communicated\u00a0with\u00a0hk2[.]upupdate[.]cn\nwhich\u00a0resolved\u00a0to\u00a0103.27.108[.]122\u00a0at\u00a0the\u00a0time\u00a0of\u00a0analysis.\n\nThe\u00a0samples\u00a0detailed\u00a0in\u00a0Table\u00a04\u00a0were\u00a0identified\u00a0by\u00a0import\u00a0hash\u00a0and\u00a0other\u00a0structural\u00a0similarities\u00a0related\u00a0to\u00a0the\u00a0UP007\n\ndropper.\u00a0They\u00a0were\u00a0uploaded\u00a0to\u00a0VirusTotal\u00a0by\u00a0the\u00a0same\u00a0submitter\u00a0on\u00a0November\u00a014,\u00a02014\u00a0and\u00a0February\u00a027,\u00a02015.\u00a0They\n\nwere\u00a0signed\u00a0with\u00a0the\u00a0same\u00a03A 72...4D\u00a0CA\u00a0and\u00a05D 11...E1 A9 certificates,\u00a0respectively.\n\nhttps://citizenlab.org/2016/04/between-hong-kong-and-burma/\n\n5/9\n\n\f2016/4/20\n\nBetween Hong Kong and Burma: Tracking UP007 and SLServer Espionage Campaigns - The Citizen Lab\n\nMD5\n\nImport\u00a0Hash\n\nC2\n\n21455a5c2496e2603f6ba911fbaaed80 820438f3f1efede11425a9cc13ae2dbd hihihihihahaha.vicp[.]cc\u00a0(113.204.17[.]59)\n\nbe378f3d66ecd38cda09508015de71f7 820438f3f1efede11425a9cc13ae2dbd 172.16.10[.]124\n\nTable\u00a04:\u00a0UP007\u00a0Variants\n\nThe\u00a0RAR\u00a0archive\u00a0detailed\u00a0in\u00a0Table\u00a05\u00a0reportedly\u00a0drops\u00a0the\u00a0same\u00a0files\u00a0responsible\u00a0for\u00a0loading\u00a0the\u00a0UP007\u00a0sample.\u00a0It\u00a0also\n\nreportedly\u00a0communicates\u00a0with\u00a059.188.12[.]123.\u00a0We\u00a0have\u00a0not\u00a0been\u00a0able\u00a0to\u00a0obtain\u00a0this\u00a0sample\u00a0directly.\n\nMD5\n\nFile\u00a0Name\n\nC2\n\n19866e7566373028799abd6844ac16d1 QiHua.rar 219.133.40[.]1,\n\n59.188.12[.]123\n\nTable\u00a05:\u00a0UP007\u00a0Variants\n\nSLServer\u00a0Malware\u00a0Family\n\nThe\u00a0SLServer\u00a0sample\u00a0we\u00a0received\u00a0was\u00a0also\u00a0recently\u00a0analyzed\u00a0and\u00a0reported\u00a0by\u00a0PwC.\u00a0It\u00a0was\u00a0presented\u00a0in\u00a0an\u00a0overview\u00a0of\n\nthreat\u00a0actors\u00a0making\u00a0use\u00a0of\u00a0the\u00a0recent\u00a0Taiwanese\u00a0presidential\u00a0election\u00a0in\u00a0email\u00a0lures\u00a0to\u00a0entice\u00a0targets\u00a0to\u00a0open\u00a0malicious\n\ndocuments.\u00a0As\u00a0noted\u00a0by\u00a0PwC,\u00a0this\u00a0file\u00a0is\u00a0a\u00a0self-extracting\u00a0archive\u00a0ultimately\u00a0responsible\u00a0for\u00a0downloading\u00a0a\u00a0binary\u00a0from\u00a0a\n\nwebsite\u00a0that\u00a0was\u00a0likely\u00a0compromised.\u00a0Like\u00a0PwC,\u00a0we\u00a0were\u00a0unable\u00a0to\u00a0obtain\u00a0the\u00a0final\u00a0Keyainst.exe\u00a0binary\u00a0due\u00a0to\u00a0the\nbehaviour\u00a0of\u00a0the\u00a0C2\u00a0during\u00a0the\u00a0time\u00a0of\u00a0analysis.\n\nBased\u00a0on\u00a0common\u00a0behavioural\u00a0characteristics\u00a0and\u00a0shared\u00a0C2\u00a0it\u00a0appears\u00a0the\u00a0downloaded\u00a0file\u00a0analyzed\u00a0by\u00a0PwC\u00a0was\n\nMD5:\u00a0e5e7dcbda781dd0bf5f5da3cccdb094d.\u00a0This\u00a0sample\u00a0was\u00a0referred\u00a0to\u00a0as\u00a0SunOrcal\u00a0by\u00a0PwC.\u00a0This\u00a0name\u00a0was\u00a0based\u00a0on\n\na\u00a0folder\u00a0misspelling.\u00a0We\u00a0refer\u00a0to\u00a0the\u00a0malware\u00a0family\u00a0as\u00a0SLServer\u00a0due\u00a0to\u00a0a\u00a0resource\u00a0dialog\u00a0in\u00a0the\u00a0file\u00a0(see\u00a0Figure\u00a06).\n\nAnother\u00a0recently\u00a0observed\u00a0instance\u00a0of\u00a0this\u00a0malware\u00a0found\u00a0on\u00a0VirusTotal\u00a0(MD5:\u00a0cfcd2a90e87156e1a811f9c7b0051002)\u00a0was\n\ndesigned\u00a0to\u00a0communicate\u00a0with\u00a0the\u00a0same\u00a0C2\u00a0server\u00a0and\u00a0contains\u00a0the\u00a0following\u00a0debug\u00a0path:\n\nFigure\u00a06:\u00a0SLServer\u00a0dialog\u00a0resource.\n\ne:\\Working\\SVNProject\\SLServer\\SLServer2.0\\release\\SLServer.pdb\n\nInterestingly,\u00a0according\u00a0to\u00a0VirusTotal,\u00a0the\u00a0previously\u00a0mentioned\u00a0UP007\u00a0dropper\u00a0fzyy.exe\u00a0was\u00a0also\u00a0observed\u00a0hosted\u00a0as\nwthk.txt\u00a0at\u00a0the\u00a0same\u00a0URL\u00a0as\u00a0this\u00a0downloaded\u00a0SLServer\u00a0sample.\u00a0The\u00a0precise\u00a0timeframes\u00a0during\u00a0which\u00a0these\u00a0samples\u00a0were\nhosted\u00a0and\u00a0changed\u00a0remains\u00a0unknown.\u00a0Table\u00a06\u00a0shows\u00a0the\u00a0timestamps\u00a0of\u00a0their\u00a0initial\u00a0upload\u00a0to\u00a0VirusTotal.\n\nFile\u00a0Name Malware\u00a0Family\n\nMD5\n\nFirst\u00a0Submission\u00a0Time\n\nwzget.exe SLServer\n\ne5e7dcbda781dd0bf5f5da3cccdb094d 2016\u00ad01\u00ad07\u00a019:03:25\u00a0UTC\n\nfzyy.exe\n\nUP007\n\nd579d7a42ff140952da57264614c37bc 2016\u00ad01\u00ad08\u00a005:21:18\u00a0UTC\n\nTable\u00a06:\u00a0Times\u00a0for\u00a0Sample\u00a0Upload\u00a0to\u00a0VirusTotal\n\nSLServer\u00a0\u2013\u00a0Possible\u00a0Second\u00a0Stage\n\nhttps://citizenlab.org/2016/04/between-hong-kong-and-burma/\n\n6/9\n\n\f2016/4/20\n\nBetween Hong Kong and Burma: Tracking UP007 and SLServer Espionage Campaigns - The Citizen Lab\n\nThe\u00a0SLServer\u00a0sample\u00a0(MD5:\u00a0e5e7dcbda781dd0bf5f5da3cccdb094d)\u00a0calls\u00a0\u201cFunctionWork\u201d\u00a0from\u00a0a\u00a0DLL:\n\nOn\u00a0VirusTotal\u00a0we\u00a0discovered\u00a0a\u00a0file\u00a0named\u00a0javaupdata.dll\u00a0(MD5:\u00a0<7332245f67b6b8a256ab22a6496b4536),\u00a0which\nexports\u00a0a\u00a0function\u00a0by\u00a0the\u00a0same\u00a0name.\u00a0Strings\u00a0in\u00a0the\u00a0SLServer\u00a0sample\u00a0also\u00a0reference\u00a0a\u00a0file\u00a0by\u00a0this\u00a0name.\u00a0When\u00a0executed,\n\nthis\u00a0DLL\u00a0contacts\u00a0210.61.12[.]153\u00a0using\u00a0SSL.\u00a0This\u00a0host\u00a0is\u00a0the\u00a0same\u00a0one\u00a0pointed\u00a0to\u00a0by\u00a0the\u00a0SLServer\u2019s\u00a0C2\u00a0domain,\nsafetyssl.security-centers[.]com.\u00a0Interestingly,\u00a0while\u00a0the\u00a0210.61.12[.]153\u00a0host\u00a0did\u00a0not\u00a0respond\u00a0to\u00a0the\u00a0SLServer\nconnections\u00a0during\u00a0analysis\u00a0time,\u00a0the\u00a0host\u00a0did\u00a0accept\u00a0the\u00a0SSL\u00a0connections\u00a0from\u00a0javaupdata.dll.\u00a0Further\u00a0analysis\u00a0of\u00a0this\nfile\u00a0is\u00a0ongoing.\n\nSLServer\u00a0Command\u00a0and\u00a0Control\u00a0Infrastructure\n\nThe\u00a0SLServer\u00a0C2\u00a0server:\u00a0safetyssl.security-centers[.]com resolved\u00a0to\u00a0the\u00a0IP\u00a0address:\u00a0210.61.12[.]153\u00a0at\u00a0the\u00a0time\nof\u00a0analysis.\u00a0This\u00a0IP\u00a0is\u00a0hosted\u00a0in\u00a0Taiwan\u00a0on\u00a0the\u00a0hosting\u00a0provider\u00a0Chunghwa\u00a0Telecom,\u00a0specifically\u00a0their\u00a0Data\u00a0Communication\n\nBusiness\u00a0Group\u00a0offering.\u00a0It\u00a0appears\u00a0to\u00a0host\u00a0the\u00a0site\u00a0of\u00a0a\u00a0Taiwanese\u00a0auto\u00a0parts\u00a0manufacturer,\u00a0Yowjung\u00a0Autoparts.\u00a0This\u00a0site\n\nmay\u00a0have\u00a0been\u00a0either\u00a0compromised\u00a0or\u00a0copied\u00a0from\u00a0a\u00a0legitimate\u00a0source.\n\nThe\u00a0domain\u00a0name\u00a0security-centers.com\u00a0was\u00a0registered\u00a0on\u00a0September\u00a011\u00a02015\u00a0by\u00a0the\u00a0e-mails:\u00a0janmiller-\ndomain@googlemail[.]com\u00a0and\u00a0an_ardyth@123mail[.]org.\u00a0Using\u00a0Passive\u00a0DNS\u00a0data\u00a0we\u00a0find\u00a0the\u00a0following\u00a0subdomains\nwere\u00a0used\u00a0in\u00a0the\u00a0time\u00a0period\u00a0after\u00a0domain\u00a0registration:\n\nsafetyssl.security-centers[.]com\n\ncomputer.security-centers[.]com\n\nsecurity-centers[.]com\n\nwww.security-centers[.]com\n\nThe\u00a0domain\u00a0computer.security-centers[.]com\u00a0was\u00a0a\u00a0C2\u00a0server\u00a0previously\u00a0reported\u00a0by\u00a0ASERT\u00a0related\u00a0to\u00a0a\u00a0sample\u00a0of\nthe\u00a0Trochilus\u00a0RAT\u00a0analyzed\u00a0in\u00a0the\u00a0report.\u00a0ASERT\u00a0retrieved\u00a0that\u00a0sample\u00a0from\u00a0the\u00a0compromised\u00a0Myanmar\u00a0Union\u00a0Election\n\nCommission\u00a0website.\u00a0The\u00a0other\u00a0subdomains\u00a0(www\u00a0and\u00a0the\u00a0the\u00a0top\u00a0level\u00a0security-centers[.]com)\u00a0are\u00a0likely\u00a0the\u00a0default\nIP\u00a0addresses\u00a0for\u00a0GoDaddy\u00a0registered\u00a0domains.\u00a0The\u00a0hosting\u00a0information\u00a0for\u00a0this\u00a0infrastructure\u00a0is\u00a0presented\u00a0in\u00a0the\u00a0Figure\u00a07.\n\nhttps://citizenlab.org/2016/04/between-hong-kong-and-burma/\n\n7/9\n\n\f2016/4/20\n\nBetween Hong Kong and Burma: Tracking UP007 and SLServer Espionage Campaigns - The Citizen Lab\n\nFigure\u00a07:\u00a0Hosting\u00a0infrastructure\u00a0over\u00a0time\u00a0for\u00a0*.security-centers[.]com\n\nSLServer\u00a0Samples\u00a0and\u00a0Variations\n\nWe\u00a0discovered\u00a0three\u00a0additional\u00a0SLServer\u00a0samples\u00a0using\u00a0VirusTotal.\u00a0\u00a0We\u00a0list\u00a0the\u00a0hash,\u00a0submission\u00a0time,\u00a0as\u00a0well\u00a0as\u00a0C2\u00a0domains\n\nassociated\u00a0with\u00a0the\u00a0sample\u00a0in\u00a0Table\u00a07.\n\nMD5\n\nFirst\u00a0Submission\n\nC2\n\nd07b2738840ce3419df651d3a0a3a246 2016\u00ad02\u00ad25\u00a001:14:15 www.olinaodi[.]com\n\n(74.126.181[.]10)\n\n397021af7c0284c28db65297a6711235 2016\u00ad02\u00ad22\u00a018:30:19 safetyssl.security\u00adcenters[.]com\n\n(210.61.12[.]153)\n\ndc195d814ec16fe91690b7e949e696f6\n\n2016\u00ad02\u00ad17\u00a011:32:02 www.olinaodi[.]com\n\n(74.126.181[.]10)\n\ncfcd2a90e87156e1a811f9c7b0051002\n\n2015\u00ad11\u00ad09\u00a005:20:33 safetyssl.security\u00adcenters[.]com\n\n(211.255.32[.]130)\n\nTable\u00a07:\u00a0SLServer\u00a0Variants\u00a0Overview\n\nRecent\u00a0Campaign\u00a0Connections\n\nIn\u00a0January\u00a02016,\u00a0Arbor\u00a0Networks\u00a0released\u00a0a\u00a0report\u00a0titled\u00a0\u201cUncovering\u00a0the\u00a0Seven\u00a0Pointed\u00a0Dagger\u201d\u00a0in\u00a0which\u00a0they\u00a0discuss\n\na\u00a0series\u00a0of\u00a0six\u00a0RAR\u00a0files\u00a0hosted\u00a0on\u00a0the\u00a0Myanmar\u00a0election\u00a0commission\u00a0website\u00a0on\u00a020\u00a0October\u00a02015.\u00a0The\u00a0focus\u00a0of\u00a0the\u00a0report\n\nwas\u00a0on\u00a0the\u00a0discovery\u00a0of\u00a0the\u00a0new\u00a0Trochilus\u00a0RAT.\u00a0However,\u00a0one\u00a0of\u00a0the\u00a0RAR\u00a0files\u00a0was\u00a0noted\u00a0as\u00a0unknown\u00a0malware.\u00a0This\u00a0sample\n\n(Security-Patch-Update.exe,\u00a0MD5:\u00a082896b68314d108141728a4112618304)\u00a0is\u00a0also\u00a0UP007,\u00a0signed\u00a0with\u00a0the\u00a05D 11 78 4F\nB8 17 65 02 3F 89 A4 F4 24 3F E1 A9 certificate\u00a0and\u00a0configured\u00a0to\u00a0communicate\u00a0with\u00a059.188.12[.]123\u00a0directly\nover\u00a0port\u00a08008,\u00a0identical\u00a0to\u00a0fzyy.exe\u00a0mentioned\u00a0above.\u00a0In\u00a0this\u00a0instance,\u00a0if\u00a0any\u00a0of\u00a0the\u00a0previously\u00a0discussed\u00a0registry\u00a0keys\nwere\u00a0present,\u00a0the\u00a0sample\u00a0will\u00a0execute\u00a0the\u00a0dropped\u00a0runas.exe\u00a0binary.\u00a0Given\u00a0this\u00a0execution,\u00a0nvsvc.exe\u00a0is\u00a0likely\u00a0also\u00a0an\nolder\u00a0component.\u00a0As\u00a0discussed\u00a0above\u00a0the\u00a0UP007\u00a0sample\u00a0we\u00a0analyzed\u00a0shares\u00a0the\u00a0same\u00a0C2\u00a0(computer.security-\ncenters[.]com)\u00a0as\u00a0the\u00a0Trochilus\u00a0RAT\u00a0sample\u00a0reported\u00a0by\u00a0ASERT.\n\nIn\u00a0November\u00a02015,\u00a0Palo\u00a0Alto\u00a0Networks\u00a0reported\u00a0on\u00a0a\u00a0newly\u00a0discovered\u00a0trojan\u00a0referred\u00a0to\u00a0as\u00a0Bookworm.\u00a0They\u00a0revealed\u00a0a\n\ncampaign\u00a0focused\u00a0on\u00a0the\u00a0targeting\u00a0of\u00a0government\u00a0entities\u00a0in\u00a0Thailand.\u00a0The\u00a0campaign\u00a0used\u00a0a\u00a0malware\u00a0family\u00a0known\u00a0as\n\nFFRAT,\u00a0and\u00a0the\u00a0sample\u00a0described\u00a0in\u00a0the\u00a0report\u00a0connected\u00a0to\u00a0the\u00a0domain\u00a0hkemail.f3322[.]org\u00a0for\u00a0command\u00a0and\ncontrol.\u00a0In\u00a0August\u00a02015,\u00a0the\u00a0same\u00a0domain\u00a0was\u00a0reportedly\u00a0used\u00a0to\u00a0host\u00a0an\u00a0instance\u00a0of\u00a0UP007\u00a0as\u00a0well.\n\nFinally,\u00a0the\u00a0relationship\u00a0between\u00a0the\u00a0SLServer\u00a0C2\u00a0www.olinaodi[.]com\u00a0and\u00a0our\u00a0previous\u00a0research\u00a0into\u00a0the\u00a0Surtr\u00a0malware\n\nfamily\u00a0was\u00a0highlighted\u00a0by\u00a0PwC\u00a0through\u00a0the\u00a0overlap\u00a0in\u00a0the\u00a0toucan6712@163[.]com\u00a0registrant.\u00a0We\u00a0tracked\u00a0malware\ncampaigns\u00a0using\u00a0the\u00a0Surtr\u00a0family\u00a0that\u00a0have\u00a0targeted\u00a0Tibetan\u00a0organizations\u00a0since\u00a02013.\n\nConclusion\n\nThis\u00a0latest\u00a0espionage\u00a0campaign\u00a0against\u00a0Hong\u00a0Kong\u00a0activists\u00a0appears\u00a0to\u00a0be\u00a0connected\u00a0to\u00a0a\u00a0broader\u00a0set\u00a0of\u00a0targets,\u00a0and\n\noperations.\u00a0The\u00a0recent\u00a0detailed\u00a0reporting\u00a0by\u00a0ASERT\u00a0makes\u00a0it\u00a0clear\u00a0that\u00a0the\u00a0UP007\u00a0malware\u00a0family\u00a0has\u00a0been\u00a0found\u00a0in\n\nprevious\u00a0campaigns\u00a0targeting\u00a0Burmese\u00a0interests.\u00a0In\u00a0addition,\u00a0the\u00a0campaigns\u00a0share\u00a0some\u00a0C2\u00a0infrastructure\u00a0with\u00a0previous\n\noperations\u00a0against\u00a0targets\u00a0in\u00a0Thailand\u00a0and\u00a0the\u00a0Tibetan\u00a0community.\u00a0The\u00a0domain\u00a0registration\u00a0connections\u00a0between\n\nSLServer\u00a0infrastructure\u00a0and\u00a0Surtr\u00a0infrastructure\u00a0also\u00a0suggests\u00a0some\u00a0level\u00a0of\u00a0potential\u00a0coordination\u00a0between\u00a0campaigns\n\ntargeting\u00a0Hong\u00a0Kong\u00a0groups\u00a0and\u00a0the\u00a0Tibetan\u00a0community.\u00a0Despite\u00a0these\u00a0connections,\u00a0it\u00a0is\u00a0unclear\u00a0if\u00a0these\u00a0campaigns\u00a0are\n\nbeing\u00a0conducted\u00a0by\u00a0the\u00a0same\u00a0threat\u00a0actor.\n\nWe\u00a0cannot\u00a0exclude\u00a0the\u00a0possibility\u00a0that\u00a0distinct\u00a0operators\u00a0have\u00a0a\u00a0degree\u00a0of\u00a0sharing\u00a0of\u00a0tools\u00a0and\u00a0infrastructure.\n\nAlternatively,\u00a0security\u00a0researcher\u00a0Ned\u00a0Moran\u00a0has\u00a0articulated\u00a0a\u00a0concept\u00a0of\u00a0a\u00a0\u201cdigital\u00a0quartermaster,\u201d\u00a0to\u00a0refer\u00a0to\u00a0an\n\nactor\u00a0that\u00a0supplies\u00a0threat\u00a0infrastructure\u00a0and\u00a0malware\u00a0development\u00a0resources\u00a0to\u00a0multiple\u00a0groups.\u00a0While\u00a0these\u00a0scenarios\n\nare\u00a0plausible,\u00a0we\u00a0do\u00a0not\u00a0have\u00a0enough\u00a0data\u00a0to\u00a0properly\u00a0assess\u00a0these\u00a0competing\u00a0hypotheses,\u00a0or\u00a0to\u00a0make\u00a0conclusive\n\nstatements\u00a0about\u00a0the\u00a0identity\u00a0of\u00a0the\u00a0threat\u00a0actors.\n\nWhat\u00a0is\u00a0clear\u00a0from\u00a0our\u00a0analysis\u00a0is\u00a0that\u00a0civil\u00a0society\u00a0groups\u00a0across\u00a0Asia\u00a0continue\u00a0to\u00a0be\u00a0targeted\u00a0by\u00a0persistent\u00a0and\u00a0organized\n\ncyber\u00a0espionage\u00a0campaigns.\u00a0Civil\u00a0society\u00a0often\u00a0lack\u00a0the\u00a0resources\u00a0and\u00a0awareness\u00a0to\u00a0defend\u00a0against\u00a0these\u00a0operations\n\nand\u00a0closer\u00a0attention\u00a0to\u00a0the\u00a0threats\u00a0they\u00a0face\u00a0is\u00a0needed.\n\nAcknowledgements\nhttps://citizenlab.org/2016/04/between-hong-kong-and-burma/\n\n8/9\n\n\f2016/4/20\n\nBetween Hong Kong and Burma: Tracking UP007 and SLServer Espionage Campaigns - The Citizen Lab\n\nAcknowledgements\n\nSpecial\u00a0thanks\u00a0to\u00a0Valkyrie-X\u00a0Security\u00a0Research\u00a0Group\u00a0and\u00a0ASERT.\u00a0We\u00a0are\u00a0grateful\u00a0to\u00a0Jason\u00a0Q.\u00a0Ng\u00a0and\u00a0Kun\u00a0Cleo\u00a0Zhang\u00a0for\n\ntranslation\u00a0assistance,\u00a0and\u00a0Adam\u00a0Senft,\u00a0John\u00a0Scott-Railton,\u00a0and\u00a0Ron\u00a0Deibert\u00a0for\u00a0comments.\n\nThis\u00a0research\u00a0was\u00a0supported\u00a0by\u00a0the\u00a0John\u00a0D\u00a0and\u00a0Catherine\u00a0T.\u00a0MacArthur\u00a0Foundation\u00a0and\u00a0the\u00a0William\u00a0and\u00a0Flora\u00a0Hewlett\n\nFoundation.\n\nIndicators\u00a0of\u00a0Compromise\n\nYara\u00a0signatures\u00a0are\u00a0available\u00a0for\u00a0the\u00a0UP007\u00a0and\u00a0SLServer\u00a0malware\u00a0families\u00a0here\n\nMD5\u00a0Hashes\n\nd579d7a42ff140952da57264614c37bc\n\nd8becbd6f188e3fb2c4d23a2d36d137b\n\n09ddd70517cb48a46d9f93644b29c72f\n\nf70b295c6a5121b918682310ce0c2165\n\nf80edbb0fcfe7cec17592f61a06e4df2\n\nd8ede9e6c3a1a30398b0b98130ee3b38\n\nce8ec932be16b69ffa06626b3b423395\n\n6a541de84074a2c4ff99eb43252d9030\n\ne0eb981ad6be0bd16246d5d442028687\n\n639c7239f40d95f677a99abb059e8338\n\nd07b2738840ce3419df651d3a0a3a246\n\n397021af7c0284c28db65297a6711235\n\ndc195d814ec16fe91690b7e949e696f6\n\ncfcd2a90e87156e1a811f9c7b0051002\n\nIP\u00a0Addresses\n\n59.188.12[.]123\n\n210.61.12[.]153\n\nDomains\n\nsafetyssl.security-centers[.]com\n\ncomputer.security-centers[.]com\n\nhkemail.f3322[.]org\n\nwww.olinaodi[.]com\n\ntenday.mysecondarydns[.]com\n\n\u00a9\u00a0Citizenlab\u00a02016\u00a0|\u00a0\u00a0Contact\u00a0\u00a0|\u00a0\u00a0RSS\u00a0\n\nhttps://citizenlab.org/2016/04/between-hong-kong-and-burma/\n\n9/9\n\n\f"], "URLs": ["http://hkemail.f3322[.]org/32.zip.", "http://103.19.85[.]89/chin.jpg.", "https://citizenlab.org/2016/04/between-hong-kong-and-burma/"], "weight": 0.0}