{
  "rule_id": 25,
  "name": "MuddyWater's Recent Activity",
  "description": "-",
  "references": [],
  "samples": [
    "anahera.biz",
    "airesis.blog",
    "centreforgovernance.uk",
    "toiles.fr",
    "171207081414203.doc",
    "apalawyers.pt",
    "andihaas.at",
    "arbeidsrechtcentrum.nl",
    "com.pk",
    "aiko.pro",
    "com.pe",
    "habibtextiles.pk",
    "www.bitp",
    "allday.gr",
    "org.ls",
    "downfile.jsp",
    "com.au",
    "idrbt.doc",
    "alphabee.fund",
    "ahc.me",
    "aianalytics.ie",
    "pengalandet.se",
    "agencereferencement.be",
    "anthaigroup.vn",
    "aminearserver.es",
    "beauty.ch",
    "iiee.edu",
    "mag.ro",
    "aipa.ca",
    "www.easy",
    "agricolavicuna.cl",
    "anotherdayinparadise.ca",
    "co.za",
    "arhiepiscopiabucurestilor.ro",
    "amika.hr",
    "amordegato.es",
    "alephit2.biz",
    "anbinni.ba",
    "ash.biz",
    "ganitis.gr",
    "www.dws",
    "apobiomedix.ca",
    "dpscdgkhan.edu",
    "altaica.ca",
    "com.ua",
    "africanpixels.zar",
    "csmtp.exe",
    "annabelle.nl",
    "com.br",
    "albertamechanical.ca",
    "ambyenta.hr",
    "www.acer",
    "www.antc",
    "www.air",
    "www.hfhl",
    "139bf1d94eb646fcbd44de40ce2163d7.doc",
    "rjoawork.bak",
    "antjetaubert.de",
    "template.php",
    "arctistrade.de",
    "aliart.nl",
    "almatours.gr",
    "amari.ro",
    "alisimple.si"
  ],
  "weight": 0.0,
  "signatures": [
    "139bf1d94eb646fcbd44de40ce2163d7",
    "40105caaa2568c7c0bb2f540532f9b7e",
    "c87799cce6d65158da97aa31a5160a0a6b6dd5a89dea312604cc66ed5e976cc9",
    "288afbe21d69e79a1cff44e2db7f491af10381bcc54436a8f900bcbd2a752a6f",
    "009cc0f34f60467552ef79c3892c501043c972be55fe936efb30584975d45ec0"
  ]
}
