{"ti_no": 1566, "rule_id": 10000566, "ti_nm": "Operation_SnowMan", "ti_desc": "", "ti_ref": [], "ti_smp": "", "ti_area": "etas", "ti_type": ["HASH", "URL"], "ti_applied": "Y", "site_tp": "rio", "del_yn": "N", "reg_dt": "", "reg_user_id": "admin", "ti_sgn": ["8455bbb9a210ce603a1b646b0d951bce", "9d20566a327076b7152bbf9ed20292c4", "0294f9280491f85d898ebe471f0fb58e", "758886e58f9ea2ff22b57cbbb015166e", "book.flnet.org", "me.scieron.com", "newss.effers.com", "cht.blankchair.com", "info.flnet.org", "vfw.org", "dll.freshdns.org", "ali.blankchair.com", "rt.blankchair.com", "icybin.flnet.org"]}