{"ti_no": 1555, "rule_id": 10000555, "ti_nm": "The Good, the Bad, and the Web Bug_ TA416 Increases Operational Tempo Against European Governments as Conflict in Ukraine Escalates _ Proofpoint US", "ti_desc": "", "ti_ref": [], "ti_smp": "", "ti_area": "etas", "ti_type": ["HASH", "URL"], "ti_applied": "Y", "site_tp": "rio", "del_yn": "N", "reg_dt": "", "reg_user_id": "admin", "ti_sgn": ["0e3e47697539f1773fb53114ab53229c0304d86ed35aec05e5f5bfdf3bd35f9a", "54b491541376bda85ffb02b9bb40b9b5adba644f08b630fc1b47392625e1e60a", "69.90.184.125", "uepspr.com"]}