{"rule_id": 198, "name": "A new APT uses DLL side-loads to “KilllSomeOne” – Sophos News", "description": "-", "references": [], "samples": ["bridge.dll", "mpsvc.dll", "Groza_1.dat", "mpsvc.pdb", "functionhex.pdb", "DISM.EXE", "bridge.dat", "UDPDLL.pdb", "Aug.exe", "AUG.exe", "dismcore.dll", "it.The", "hex.dll", "SafeGuard.exe", "dbg.exe", "akm.dat", "Mediae.exe", "adobe.dat", "hex.pdb", "DismCore.pdb", "msvcp120.dll", "msvcr120.dll", "Updates.exe"], "weight": 0.0, "signatures": ["https://news.sophos.com/en-us/2020/11/04/a-new-apt-uses-dll-side-loads-to-killlsomeone/"]}