{"rule_id": 271, "name": "Crouching_tiger_hidden_dragon", "description": "-", "references": [], "samples": ["online.wsj", "www.cbc", "www.mcc", "www.xd", "www.faw", "comac.cc", "www.crhc", "www.ch", "www.crcc", "www.chng", "www.cfgc", "www.ciic", "www.crc", "www.sdic", "www.hpec", "www.dfmc", "www.chd", "www.cgdc", "www.cec", "www.cssc", "china.html", "www.cam", "www.csic", "www.csgc", "www.cpgc", "www.hfjt", "happens.html", "www.avic", "www.cfhi", "www.sgcc", "www.cmgb", "www.ceec", "SB10001424052748704814204575507353221141616.html", "www.casc", "www.ccgc", "100728chinareport_0.pdf", "www.cabr", "www.cmhk", "www.wri", "1.OG", "www.csg", "www.crsc", "www.cpni", "www.cetc"], "weight": 0.0, "signatures": ["http://www.hualu.com.cn", "http://www.bgrimm.com", "http://www.sdic.com.cn", "http://www.cnshipping.com", "http://www.comac.cc", "http://www.chinatex.com", "http://www.chinaunicom.com.cn", "http://www.chinasilk.com", "http://www.cnmc.com.cn", "http://www.ceec.net.cn", "http://www.crc.com.hk", "http://www.cetc.com.cn", "http://www.cpni.gov.uk", "http://www.ccteg.cn", "http://www.namkwong.com", "http://www.chalco.com.cn", "http://www.sinopharm.com", "http://www.cpicorp.com.cn", "http://www.xd.com.cn", "http://www.csgc.com.cn", "http://www.cscec.com", "http://www.fbi.gov/", "http://www.grinm.com", "http://www.cadreg.com.cn", "http://english.comac.cc/", "http://www.chtgc.com", "http://www.sinoma.cn", "http://www.cam.com.cn", "http://www.chinasalt.com.cn", "http://www.zhzrgs.com.cn", "http://www.snptc.com.cn", "http://www.cnecc.com", "http://www.cofco.com", "http://www.cmgb.com.cn", "http://www.cabr.com.cn", "http://www.chinagoldgroup.com", "http://www.wri.com.cn", "http://www.sinolight.cn", "http://www.cmhk.com", "http://www.potevio.com", "http://www.cpgc.cn", "http://www.alcatel-", "http://www.10086.cn", "http://www.hpec.com", "http://www.ccgrp.com.cn", "http://www.sinosteel.com", "http://www.spacechina.com", "http://www.dongfang.com", "http://www.sinochem.com", "http://www.datanggroup.cn", "http://www.airchinagroup.com", "http://www.chinacoal.com", "http://www.cnadc.com.cn", "http://www.ch.com.cn", "http://www.cfhi.com", "http://www.avic.com.cn", "http://www.sinopecgroup.c", "http://www.csg.cn", "http://www.hkcts.com", "http://www.cgnpc.com.cn", "http://www.crsc.cn", "http://www.bbc.co.uk/news/technology-11388018", "http://www.crmsc.com.cn", "http://www.ciecc.com.cn", "http://www.cnnc.com.cn", "http://www.casc.com.cn", "http://www.csrgc.com.cn", "http://www.crecg.com", "http://www.mcc.com.cn", "http://www.china-cdt.com", "http://www.cncec.cn", "http://www.sinomach.com.cn", "http://www.chd.com.cn", "http://www.wisco.com.cn", "http://www.cisri.com.cn", "http://www.hfjt.com.cn", "http://www.cncrc.com.cn", "http://www.genertec.com.cn", "http://www.sinotrans-csc.com", "http://www.citsgroup.com.cn", "http://www.xxcig.com", "http://www.cec.com.cn", "http://www.travelskyholding", "http://www.shenhuagroup.com.cn", "http://www.dfmc.com.cn", "http://www.cctgroup.com.cn", "http://www.ciic.com.cn", "http://www.ansteelgroup.com", "http://www.chinatelecom.com.cn", "http://www.ccgc.cn", "http://www.uschamber.com/sites/default/files/reports/100728chinareport_0.pdf", "http://online.wsj.com/article/SB10001424052748704814204575507353221141616.html", "http://www.chinaoct.com", "http://www.chinacnr.com", "http://www.cssc.net.cn", "http://www.csic.com.cn", "http://www.baosteel.com", "http://www.cgdc.com.cn", "http://www.cnbm.com.cn", "http://www.norincogroup.com.cn", "http://www.cosco.com", "http://www.ctgpc.com.cn/", "http://www.crcc.cn", "http://googleblog.blogspot.com/2010/01/new-approach-to-china.html", "http://www.cecic.com.cn", "http://www.scribd.com/doc/13731776/Tracking-GhostNet-Investigating-a-Cyber-", "http://www.sinograin.com.cn", "http://www.chng.com.cn", "http://www.minmetals.com.cn", "http://www.sgcc.com.cn", "http://www.bbc.co.uk/news/world-asia-pacific-11505164", "http://www.casic.com.cn", "http://www.cbc.ca/news/world/story/2012/02/15/nortel-hacking-shields-as-it-", "http://www.cnooc.com.cn", "http://www.cfgc.cn", "http://www.faw.com.cn", "http://www.china-", "http://www.csair.cn", "http://www.zhongguodianjian.com", "http://www.cnacgc.com", "http://www.cnpc.com.cn/cn", "http://www.apcoworldwide.com/", "http://www.cnaf.com", "http://www.ceair.com", "http://www.crhc.cn/n127514", "http://www.chemchina.com"]}