{
  "rule_id": 260,
  "name": "tickgroupavar201920191111chaminseokpublish-191126231730",
  "description": "-",
  "references": [],
  "samples": [
    "CRYPTBASE.DLL",
    "msupdata.ex",
    "Linkinfo.dll",
    "apphelp.dll",
    "CRYPTBASE.dll",
    "minseok.cha",
    "basev1.xsd",
    "netutils.dll",
    "m32.exe",
    "build.exe",
    "l.dat",
    "mi2.exe",
    "keyll.exe",
    "mi.exe",
    "m6.exe",
    "wincrypt.dll",
    "shadowDawn.exe",
    "intelamt.tmp",
    "FlashHistory.dat",
    "loadSetup.pdb",
    "iff.exe",
    "apihex.dat",
    "msupdata.exe",
    "Cliend.exe",
    "ALYAC25.exe",
    "m3.exe",
    "steganography.exe",
    "ALYAC25.EXE",
    "hwp70.exe",
    "IPPEManager.exe",
    "main.html",
    "04_cgview_01.html",
    "msp.exe",
    "comhost.exe",
    "peacenet.go",
    "MSUPDATA.EXE",
    "Credentials.csv",
    "svcmgr.exe",
    "ls.tmp",
    "campaigns.html",
    "tmp.dat",
    "k6.dll",
    "dt.tmp",
    "BrStMonW.exe",
    "mim6.exe",
    "linkinfo.dll",
    "Cryptbase.dll",
    "BrWeb.dll",
    "wsmt.exe"
  ],
  "weight": 0.0,
  "signatures": [
    "http://updata.saranmall.com/script/main.html",
    "https://www.lac.co.jp/english/report/2016/11/04_cgview_01.html"
  ]
}
